COPYING
MANIFEST.in
README
health_invoice_view.xml
setup.py
./__init__.py
./__tryton__.py
./health_invoice.py
./tests/__init__.py
./tests/test_health_invoice.py
./wizard/__init__.py
./wizard/wizard_appointment_invoice.py
./wizard/wizard_create_lab_invoice.py
./wizard/wizard_prescription_invoice.py
icons/README
icons/invoice.svg
locale/el.po
locale/es_ES.po
locale/fa.po
locale/fr_FR.po
locale/it.po
security/access_rights.xml
trytond_health_invoice.egg-info/PKG-INFO
trytond_health_invoice.egg-info/SOURCES.txt
trytond_health_invoice.egg-info/dependency_links.txt
trytond_health_invoice.egg-info/entry_points.txt
trytond_health_invoice.egg-info/not-zip-safe
trytond_health_invoice.egg-info/requires.txt
trytond_health_invoice.egg-info/top_level.txt
wizard/appointment_invoice.xml
wizard/create_lab_invoice.xml
wizard/prescription_invoice.xml