Metadata-Version: 1.1
Name: trytond-health-invoice
Version: 1.4.4
Summary:  
